LICENSE
MANIFEST.in
README.rst
setup.py
sentry_elastic_nodestore/__init__.py
sentry_elastic_nodestore/backend.py
sentry_elastic_nodestore/models.py
sentry_elastic_nodestore.egg-info/PKG-INFO
sentry_elastic_nodestore.egg-info/SOURCES.txt
sentry_elastic_nodestore.egg-info/dependency_links.txt
sentry_elastic_nodestore.egg-info/not-zip-safe
sentry_elastic_nodestore.egg-info/requires.txt
sentry_elastic_nodestore.egg-info/top_level.txt
sentry_elastic_nodestore/management/__init__.py
sentry_elastic_nodestore/management/commands/__init__.py
sentry_elastic_nodestore/management/commands/elastic_template.py
sentry_elastic_nodestore/templates/sentry.json