Metadata-Version: 1.1
Name: sentry-elastic-nodestore
Version: 0.0.2
Summary: Sentry nodestore Elasticsearch backend
Home-page: https://github.com/hellysmile/sentry_elastic_nodestore
Author: hellysmile@gmail.com
Author-email: hellysmile@gmail.com
License: UNKNOWN
Keywords: sentry,elasticsearch,nodestore,backend
Platform: UNKNOWN
Classifier: Development Status :: 5 - Production/Stable
Classifier: Intended Audience :: Developers
Classifier: License :: OSI Approved :: Apache Software License
Classifier: Operating System :: POSIX
Classifier: Operating System :: MacOS :: MacOS X
Classifier: Operating System :: Microsoft :: Windows
Classifier: Programming Language :: Python
Classifier: Operating System :: OS Independent
